VITAE/VITAE.py
VITAE/__init__.py
VITAE/inference.py
VITAE/metric.py
VITAE/model.py
VITAE/train.py
VITAE/utils.py
pyvitae-2.1.0.dist-info/LICENSE
pyvitae-2.1.0.dist-info/METADATA
pyvitae-2.1.0.dist-info/WHEEL
pyvitae-2.1.0.dist-info/top_level.txt
pyvitae-2.1.0.dist-info/RECORD
